interactiveshellsubproc/README.MD
interactiveshellsubproc/__init__.py
interactiveshellsubproc/requirements.txt
interactiveshellsubproc/thirdparty.json
interactiveshellsubproc-0.13.dist-info/LICENSE.rst
interactiveshellsubproc-0.13.dist-info/METADATA
interactiveshellsubproc-0.13.dist-info/WHEEL
interactiveshellsubproc-0.13.dist-info/top_level.txt
interactiveshellsubproc-0.13.dist-info/RECORD
