Metadata-Version: 2.1
Name: interactiveshellsubproc
Version: 0.13
Summary: Interactive subprocess Instances for cmd.exe, powershell.exe, adb.exe, bash.exe without deadlocks - pure Python, no dependencies
Home-page: https://github.com/hansalemaos/interactiveshellsubproc
Author: Johannes Fischer
Author-email: aulasparticularesdealemaosp@gmail.com
License: MIT
Keywords: shell,deadlock,interactive,bidirectional 
Classifier: Development Status :: 4 - Beta
Classifier: Programming Language :: Python :: 3 :: Only
Classifier: Programming Language :: Python :: 3.10
Classifier: Topic :: Software Development :: Libraries :: Python Modules
Classifier: Topic :: Utilities
License-File: LICENSE.rst
Requires-Dist: exceptdrucker
Requires-Dist: procciao
